kafka_ease/__init__.py
kafka_ease/command.py
kafka_ease/kafka_handler.py
kafka_ease/main.py
kafka_ease/read_file.py
kafka_ease/validator.py
kafka_ease-1.0.3.dist-info/LICENSE
kafka_ease-1.0.3.dist-info/METADATA
kafka_ease-1.0.3.dist-info/WHEEL
kafka_ease-1.0.3.dist-info/entry_points.txt
kafka_ease-1.0.3.dist-info/top_level.txt
kafka_ease-1.0.3.dist-info/RECORD
