Metadata-Version: 2.1
Name: kafka-ease
Version: 1.0.3
Summary: Automating the creation of topics and ACLs is a common task for Kafka administrators. This repository contains a set of utilities to automate these tasks.
Home-page: https://rdomenzain.github.io/kafka-ease/
Author: Ricardo Domenzain
Author-email: richydomenzain@gmail.com
Maintainer: Ricardo Domenzain
Maintainer-email: richydomenzain@gmail.com
License: GPLv3
Project-URL: Bug Tracker, https://github.com/rdomenzain/kafka-ease/issues
Project-URL: Changelog, https://github.com/rdomenzain/kafka-ease/releases
Keywords: kafka,kafka-topics,kafka-acls,kafka-administration,kafka-automation
Classifier: Programming Language :: Python :: 3
Classifier: License :: OSI Approved :: GNU General Public License v3 (GPLv3)
Classifier: Intended Audience :: Developers
Requires-Python: >=3.8
License-File: LICENSE
Requires-Dist: click >=8.1.3
Requires-Dist: kafka-python >=2.0.2
Requires-Dist: PyYAML
Requires-Dist: python-dotenv
